rlanutils/__init__.py
rlanutils/cv/__init__.py
rlanutils/cv/geometry.py
rlanutils/cv/graphics.py
rlanutils/data_structure/__init__.py
rlanutils/data_structure/set.py
rlanutils/io/__init__.py
rlanutils/io/args.py
rlanutils/io/fs.py
rlanutils/io/indices.py
rlanutils/io/network.py
rlanutils/io/parallelism.py
rlanutils/plot/__init__.py
rlanutils/plot/color.py
rlanutils-0.1.11.dist-info/METADATA
rlanutils-0.1.11.dist-info/WHEEL
rlanutils-0.1.11.dist-info/top_level.txt
rlanutils-0.1.11.dist-info/RECORD
