Metadata-Version: 2.1
Name: rlanutils
Version: 0.1.11
Summary: A handy tool that make your day to day programming much easier. 
Home-page: https://gitlab.com/rlan/rlanutils
Author: brianlan
Author-email: brianlanbo@gmail.com
Requires-Dist: numpy
Requires-Dist: scipy
Requires-Dist: tqdm
Requires-Dist: matplotlib
Requires-Dist: pytest
Requires-Dist: pyyaml
